send_3_test/__init__.py
send_3_test/_version.py
send_3_test-0.1.0.data/data/share/jupyter/labextensions/send-3-test/build_log.json
send_3_test-0.1.0.data/data/share/jupyter/labextensions/send-3-test/package.json
send_3_test-0.1.0.data/data/share/jupyter/labextensions/send-3-test/schemas/send-3-test/package.json.orig
send_3_test-0.1.0.data/data/share/jupyter/labextensions/send-3-test/schemas/send-3-test/plugin.json
send_3_test-0.1.0.data/data/share/jupyter/labextensions/send-3-test/schemas/send-3-test/settings.json
send_3_test-0.1.0.data/data/share/jupyter/labextensions/send-3-test/static/lib_index_js.da4dd467c816b6565be4.js
send_3_test-0.1.0.data/data/share/jupyter/labextensions/send-3-test/static/lib_index_js.da4dd467c816b6565be4.js.map
send_3_test-0.1.0.data/data/share/jupyter/labextensions/send-3-test/static/remoteEntry.091fbf48cb6f631de52f.js
send_3_test-0.1.0.data/data/share/jupyter/labextensions/send-3-test/static/remoteEntry.091fbf48cb6f631de52f.js.map
send_3_test-0.1.0.data/data/share/jupyter/labextensions/send-3-test/static/style.js
send_3_test-0.1.0.data/data/share/jupyter/labextensions/send-3-test/static/style_index_js.1e0b4113d646285e9e27.js
send_3_test-0.1.0.data/data/share/jupyter/labextensions/send-3-test/static/style_index_js.1e0b4113d646285e9e27.js.map
send_3_test-0.1.0.data/data/share/jupyter/labextensions/send-3-test/install.json
send_3_test-0.1.0.dist-info/METADATA
send_3_test-0.1.0.dist-info/WHEEL
send_3_test-0.1.0.dist-info/licenses/LICENSE
send_3_test-0.1.0.dist-info/RECORD
