Metadata-Version: 2.1
Name: send_3_test
Version: 0.1.0
Summary: A JupyterLab extension.
Project-URL: Homepage, https://github.com/github_username/send-3-test
Project-URL: Bug Tracker, https://github.com/github_username/send-3-test/issues
Project-URL: Repository, https://github.com/github_username/send-3-test.git
Author-email: Raphael Marietan <me@test.com>
License: BSD 3-Clause License
License-File: LICENSE
Classifier: Framework :: Jupyter
Classifier: Framework :: Jupyter :: JupyterLab
Classifier: Framework :: Jupyter :: JupyterLab :: 4
Classifier: Framework :: Jupyter :: JupyterLab :: Extensions
Classifier: Framework :: Jupyter :: JupyterLab :: Extensions :: Prebuilt
Classifier: License :: OSI Approved :: BSD License
Classifier: Programming Language :: Python
Classifier: Programming Language :: Python :: 3
Classifier: Programming Language :: Python :: 3.8
Classifier: Programming Language :: Python :: 3.9
Classifier: Programming Language :: Python :: 3.10
Classifier: Programming Language :: Python :: 3.11
Requires-Python: >=3.8
Requires-Dist: jupyterlab<5.0.0a0,>=3.5.3
